read_version.py
read_version-0.3.2.dist-info/LICENSE
read_version-0.3.2.dist-info/METADATA
read_version-0.3.2.dist-info/WHEEL
read_version-0.3.2.dist-info/entry_points.txt
read_version-0.3.2.dist-info/top_level.txt
read_version-0.3.2.dist-info/RECORD
