Metadata-Version: 2.1
Name: read-version
Version: 0.3.2
Summary: Extract your project's __version__ variable
Home-page: https://github.com/jwodder/read_version
Author: John Thorvald Wodder II
Author-email: read-version@varonathe.org
License: MIT
Project-URL: Source Code, https://github.com/jwodder/read_version
Project-URL: Bug Tracker, https://github.com/jwodder/read_version/issues
Keywords: packaging,setuptools,version
Platform: UNKNOWN
Classifier: Development Status :: 7 - Inactive
Classifier: Programming Language :: Python :: 2
Classifier: Programming Language :: Python :: 3
Classifier: Programming Language :: Python :: 3.6
Classifier: Programming Language :: Python :: 3.7
Classifier: Programming Language :: Python :: 3.8
Classifier: Programming Language :: Python :: 3.9
Classifier: Programming Language :: Python :: Implementation :: CPython
Classifier: Programming Language :: Python :: Implementation :: PyPy
Classifier: License :: OSI Approved :: MIT License
Classifier: Framework :: Setuptools Plugin
Classifier: Intended Audience :: Developers
Classifier: Topic :: Software Development :: Libraries :: Python Modules
Classifier: Topic :: System :: Software Distribution
Requires-Python: ~=3.6
License-File: LICENSE
Requires-Dist: setuptools
Provides-Extra: toml
Requires-Dist: toml ; extra == 'toml'
